{"stat.useItem.35":6,"achievement.openInventory":40,"stat.useItem.145":1,"stat.jump":136,"achievement.exploreAllBiomes":{"value":0,"progress":["Plains"]},"stat.useItem.57":316,"stat.useItem.3":4,"stat.useItem.383":2,"stat.useItem.77":7,"stat.drop":1,"stat.flyOneCm":389108,"stat.useItem.29":9,"stat.leaveGame":6,"stat.useItem.356":9,"stat.useItem.330":1,"stat.useItem.331":39,"stat.useItem.69":3,"stat.diveOneCm":218,"stat.walkOneCm":77768,"stat.swimOneCm":46,"stat.useItem.44":3,"stat.useItem.42":658,"stat.horseOneCm":14543,"stat.playOneMinute":72991,"stat.useItem.20":150}