{"stat.useItem.6":119,"stat.useItem.7":77,"stat.useItem.17":54,"stat.useItem.19":2,"stat.useItem.148":2,"achievement.openInventory":161,"stat.jump":366,"achievement.exploreAllBiomes":{"value":0,"progress":["Plains"]},"stat.killEntity.Cow":1,"stat.useItem.1":406,"stat.useItem.3":5,"stat.minecartOneCm":31370,"stat.useItem.5":132,"stat.climbOneCm":2006,"stat.useItem.389":1,"stat.damageDealt":590,"stat.useItem.131":5,"stat.drop":6,"stat.leaveGame":11,"stat.useItem.330":1,"stat.useItem.139":21,"stat.swimOneCm":11037,"stat.walkOneCm":272298,"stat.diveOneCm":11729,"stat.useItem.276":6,"stat.useItem.44":122,"stat.useItem.42":314,"stat.useItem.41":21,"stat.useItem.35":186,"stat.useItem.324":1,"stat.useItem.323":1,"stat.useItem.85":59,"stat.useItem.86":1,"stat.useItem.87":4,"stat.mobKills":5,"stat.useItem.328":5,"stat.killEntity.Chicken":3,"stat.useItem.272":1,"stat.useItem.128":30,"stat.useItem.170":47,"stat.useItem.259":317,"stat.useItem.96":3,"stat.useItem.158":10,"stat.useItem.24":55,"stat.flyOneCm":2139791,"stat.useItem.97":17,"stat.useItem.98":623,"stat.killEntity.Pig":1,"stat.useItem.69":3,"stat.useItem.355":4,"stat.useItem.351":89,"stat.useItem.66":1,"stat.useItem.65":4,"stat.useItem.397":1,"stat.useItem.114":3,"stat.playOneMinute":316320,"stat.useItem.22":23,"stat.useItem.23":10,"stat.useItem.20":19}